dandan/__init__.py
dandan/error.py
dandan/logger.py
dandan/query.py
dandan/system.py
dandan/traffic.py
dandan/utils.py
dandan/value.py
dandan-0.7.5.dist-info/METADATA
dandan-0.7.5.dist-info/WHEEL
dandan-0.7.5.dist-info/top_level.txt
dandan-0.7.5.dist-info/zip-safe
dandan-0.7.5.dist-info/RECORD
